Metadata-Version: 2.4
Name: qatg
Version: 0.8.2
Summary: An open-source quantum automatic test generator, compatible with Qiskit.
Home-page: https://github.com/NTU-LaDS-II/qATG
Author: Chen-Hung Wu, Chin-Yang Jen, Ching-Huan Wang, Cheng-Yun Hsieh, Cynthia Kuan, Hsien-Fu Hsiao, John Wei, Jiun-Yun Li, James Chien-Mo Li
Author-email: lads427@gmail.com
Maintainer: NTU-LADS-II
License: BSD 3-clause
License-File: LICENSE.txt
Requires-Dist: qiskit>=1.0.2
Requires-Dist: qiskit-aer>=0.14.1
Requires-Dist: pylatexenc>=2.10
Requires-Dist: scipy>=1.7.1
Requires-Dist: ipympl>=0.9.2
Requires-Dist: numpy>=1.20.3
Dynamic: author
Dynamic: author-email
Dynamic: home-page
Dynamic: license
Dynamic: license-file
Dynamic: maintainer
Dynamic: requires-dist
Dynamic: summary
